pyrdle/__init__.py
pyrdle/best_word_search.py
pyrdle/lang.py
pyrdle/play.py
pyrdle/wordle.py
pyrdle-0.0.1.dev0.dist-info/LICENSE
pyrdle-0.0.1.dev0.dist-info/METADATA
pyrdle-0.0.1.dev0.dist-info/WHEEL
pyrdle-0.0.1.dev0.dist-info/entry_points.txt
pyrdle-0.0.1.dev0.dist-info/top_level.txt
pyrdle-0.0.1.dev0.dist-info/RECORD
