Metadata-Version: 2.1
Name: pyrdle
Version: 0.0.1.dev0
Summary: Play Wordle interactively in the CLI/GUI. Also contains various algorithms to defeat the game.
Home-page: https://github.com/cthoyt/pyrdle
Author: Charles Tapley Hoyt
Author-email: cthoyt@gmail.com
Maintainer: Charles Tapley Hoyt
Maintainer-email: cthoyt@gmail.com
License: MIT
Download-URL: https://github.com/cthoyt/pyrdle/releases
Project-URL: Bug Tracker, https://github.com/cthoyt/pyrdle/issues
Keywords: caching,file management
Platform: UNKNOWN
Classifier: Development Status :: 4 - Beta
Classifier: Environment :: Console
Classifier: License :: OSI Approved :: MIT License
Classifier: Operating System :: OS Independent
Classifier: Programming Language :: Python
Classifier: Programming Language :: Python :: 3.9
Classifier: Programming Language :: Python :: 3.10
Classifier: Programming Language :: Python :: 3 :: Only
Requires-Python: >=3.9
License-File: LICENSE
Requires-Dist: matplotlib
Requires-Dist: pandas
Requires-Dist: seaborn
Requires-Dist: tqdm
Requires-Dist: english-words
Requires-Dist: pyrdle
Requires-Dist: rich
Requires-Dist: click
Requires-Dist: class-resolver
Provides-Extra: docs
Requires-Dist: sphinx ; extra == 'docs'
Requires-Dist: sphinx-rtd-theme ; extra == 'docs'
Requires-Dist: sphinx-click ; extra == 'docs'
Requires-Dist: sphinx-autodoc-typehints ; extra == 'docs'
Requires-Dist: sphinx-automodapi ; extra == 'docs'
